[
  {
    "zip": "10309",
    "polylines": [
      "kkpvFlc|cMzLrq@hJiCxbAg~@bp@sTze@}HvZdCnh@_ZdOf@??~Pzb@r@fBfM|`Adh@`w@r@dANdD~Bnh@NdD??qj@dM_EyFu^tLmWnSb@r^mKrV??kAiBMAk_AeFyjA~d@qRu^et@{tABae@Dac@?[e@g@cLqL??iHmn@x@qFbE_E"
    ]
  },
  {
    "zip": "10453",
    "polylines": [
      "{~jxFbp`bM~p@hc@vQ`VwBbGnFhE~CoA??oAfiB??{EsDoYiU_OyIqFkCmKoF??bGRbBkHuIwEaLoM{Je[z@_NzOwt@"
    ]
  },
  {
    "zip": "11201",
    "polylines": [
      "}fmwF`ipbMrx@_@tHwBzFeEv@q_@dUaC??m@tf@pDdh@nb@jW??e[xeAvKlENpNmDxV??yCsFaCeGkCsDwBgEkCwBwBqAkCy@cB{@_DoA_DoAaBkDeGo@{EcBiBcAqBgAsDoAsDcBwBoAwB{@cPsKiJkKr@uH_CqNGQdAgN{Aq^GsH"
    ]
  },
  {
    "zip": "11215",
    "polylines": [
      "ydhwFpyqbMwAiDp@wClO_j@jChAtVm~@??fHiD??xBbFxIfH|RbBxZl]zPkZfAP??uDvJxFvZtMrMdn@}GpUhu@??kQp^??gObY{SrW_~@{`Air@rh@??gX_SiC_F|AeRkBsDk@jAmSwJ"
    ]
  },
  {
    "zip": "10123",
    "polylines": []
  },
  {
    "zip": "11229",
    "polylines": [
      "sxzvFlzjbMy^ko@??~O_BxA}B{AwCh\\{`@mD}G~E_OlSwUlM~T`]e`@bEnHnDcD`{@scA??vB_CpBlTfAzYwBdGsZnYo\\vH??bRdgD??utAbJi[bH??mEc{@"
    ]
  },
  {
    "zip": "11375",
    "polylines": []
  },
  {
    "zip": "11413",
    "polylines": [
      "a_jwFdvbaMl[s~A??r[nJjk@fXpq@`_@lHxJ~N~Jfj@bXfHoL|@{Jb{@aWbL`C{[z[cdA|wB??e@{HeLv@iR}By[eL}a@aFiMd@sIeg@}\\rVwKbD??{MEgIa\\pG{D}Mg`@qIsN"
    ]
  },
  {
    "zip": "11361",
    "polylines": []
  },
  {
    "zip": "10282",
    "polylines": []
  },
  {
    "zip": "11360",
    "polylines": [
      "wv}wF~mkaMbEyG{J}x@{XjA[aA??gAk_@EI??tEwItj@cYfCBtBzTll@sj@vOmC`\\cU??}HnLlEvZaBlNyOvEkHdGvEpUjR_DtTvjA??wZlL??gA{Fye@jDz@lPy`@pG{Ma]aMjK"
    ]
  },
  {
    "zip": "11374",
    "polylines": []
  },
  {
    "zip": "11412",
    "polylines": []
  },
  {
    "zip": "10095",
    "polylines": []
  },
  {
    "zip": "11228",
    "polylines": [
      "iw~vFjiwbMxLiV??ry@y_B??fTfU??zyAz{A??qCtZ??oZi[qCrGbCfGq@pIsNn[m]}IwBhF{AvDdRdJeBfFgS}HwSiQh@uAq\\qXqk@kM"
    ]
  },
  {
    "zip": "10122",
    "polylines": []
  },
  {
    "zip": "11214",
    "polylines": [
      "sy{vFngtbMlTg_@dGgEvSql@pDG??luC_]z@{I??OtKlIhPtMpHvApEeLxgAmCvCHbf@vJv^??aZk[ck@qb@aVtFsGzAcQnZsJtPw@rAWlCaCrW??{yA{{A"
    ]
  },
  {
    "zip": "10452",
    "polylines": [
      "kqhxFlwbbMb`@nK??zEbBja@n_@jMnF??nUjWgJnZ{@vQnB~I??sYbAsNoAug@wScSgHa@S??nAgiB"
    ]
  },
  {
    "zip": "10308",
    "polylines": [
      "_fnvFjpncMfJ|[`KnKt^aB`L|P??aMna@xBnCcCxFsx@b~@qs@rLw\\fC??iMyl@yP}NoKsO~`@cg@hPcIrCPtPbQbQwHeHqX~E{]bIiLdPfX~L}R"
    ]
  },
  {
    "zip": "11216",
    "polylines": [
      "wmjwFvrjbMoAaSmC\\eAyQjDK??bu@aJ_Cwa@??pQuB??vBoLl\\vd@{@za@`f@rB??cE`_A??co@iPu~@lK??kPca@"
    ]
  },
  {
    "zip": "10120",
    "polylines": []
  },
  {
    "zip": "11362",
    "polylines": [
      "_yxwFn|caM_A}KdKyIyMw{@qS{V_SmO??rpAyaC???bQtBhOhKrN??fQlJ??sAh@|@fEbYxVfOjEnKtKdJhR??~CxE??cKUaJjCwm@rv@}]d]kR|k@YlH??_SiY"
    ]
  },
  {
    "zip": "10040",
    "polylines": [
      "gjlxFn_gbMkM_F[iF~FiUvg@_ZwHkIrAmQ??vYpVpw@fg@??wCjGeZuJsYrcAwh@s`@kHaB"
    ]
  },
  {
    "zip": "10281",
    "polylines": []
  },
  {
    "zip": "10280",
    "polylines": []
  },
  {
    "zip": "10055",
    "polylines": []
  },
  {
    "zip": "10041",
    "polylines": [
      "iamwFn{ubMdDcDlI|S??yEp@w@uFaFuH"
    ]
  },
  {
    "zip": "11411",
    "polylines": []
  },
  {
    "zip": "10069",
    "polylines": []
  },
  {
    "zip": "11377",
    "polylines": []
  },
  {
    "zip": "11363",
    "polylines": []
  },
  {
    "zip": "10121",
    "polylines": []
  },
  {
    "zip": "11203",
    "polylines": [
      "q|dwFjihbMe@is@??hv@g}@??tA}AbJm@~y@qB??xl@deAdBrO??NxDmL|R{Mj@bC~z@iGd@??cFqQe_BhJ??oRx@mSc]UaP"
    ]
  },
  {
    "zip": "11217",
    "polylines": [
      "ycjwFnynbMrLoA??JfDnHq@dUuOp^vI`\\kL??uVl~@kCiAmO~i@q@vCvAhD??}DrB_EdLmJsF??ob@kWqDeh@l@uf@"
    ]
  },
  {
    "zip": "10451",
    "polylines": [
      "wkexFt`gbMoB_Jz@wQfJoZoUkW??f@kCfE{@~HfE~Hs]f@gTfEoUj\\rS??wBbLSjW~WrIvQnK??~f@faA??oU~CgOSoAg@s]S_z@~D"
    ]
  },
  {
    "zip": "10455",
    "polylines": [
      "otcxFbdabMzYon@??xi@vm@??p@pM{En_@w[nbA??wQoK_XsIRkWvBcL??rDvBrImk@kCwGcGwB"
    ]
  },
  {
    "zip": "10469",
    "polylines": [
      "sbpxFv}waMnZcrAgJkW??b[gOrjA_b@zTsNjRfOwQo}@wGgJ??jCcBrIrNjCsDcGsIcBgJ??zm@jz@??oFf@wQvkB{@jqB??{fAwBsq@cLce@_S"
    ]
  },
  {
    "zip": "11213",
    "polylines": [
      "ylhwF|zgbMo@aR~Wcl@zNwN`v@xC??rOfd@??d@hs@??mDQ_KxO_Ax`@mUw@??af@sBz@{a@m\\wd@wBnL"
    ]
  },
  {
    "zip": "10119",
    "polylines": []
  },
  {
    "zip": "11207",
    "polylines": [
      "ozjwFffbbM|Hyg@??`YwBfd@o\\sSkO`BmWlBgB??bI_GcD_Jb_BiVvTqJjZ{RbEmJdTmOxD|L_BnXt[{S??lEbM_^zUzTrp@`HoI~IzD??yh@hd@rEfMw@bAaVlD`@lF??kTmA}zAfW??{SKok@dgAyApC??yGcH}G_HkZmZ"
    ]
  },
  {
    "zip": "10045",
    "polylines": []
  },
  {
    "zip": "11429",
    "polylines": [
      "ksnwFx|caMyZyrBeMyQoAgO??r{@yP??`D{AnA?pp@y@??IdYiCAuA`tAhF`]??mu@~Vh@~C??cSbB"
    ]
  },
  {
    "zip": "11367",
    "polylines": []
  },
  {
    "zip": "11373",
    "polylines": []
  },
  {
    "zip": "11415",
    "polylines": []
  },
  null,
  {
    "zip": "11372",
    "polylines": []
  },
  {
    "zip": "11414",
    "polylines": []
  },
  {
    "zip": "11366",
    "polylines": []
  },
  {
    "zip": "11428",
    "polylines": [
      "suqwFjn_aMpIpAtXgHT{J??xObI??nAfOdMxQxZxrB??c[hZ??_Vcq@sm@clAtD{YeEsN"
    ]
  },
  {
    "zip": "10044",
    "polylines": [
      "_qywFvaibMbOxI~w@jp@xVlY~GtMs@dD}IyBoxB{iBqC_G?{EnFiAxIrAjMvQ"
    ]
  },
  {
    "zip": "11206",
    "polylines": [
      "aflwFjdfbMxGvIj]bUjLdfA??kDJdAxQlC]nA`S??{q@bIyBdBdAzS??J`CqFcAo\\ok@k\\zBqIy_AqH_d@??r{@}UnKkUfHfH"
    ]
  },
  {
    "zip": "10118",
    "polylines": []
  },
  {
    "zip": "11212",
    "polylines": [
      "knewFxoebMyy@kgC??|zAgWjTlA??xG~MhInq@u@tbA??iv@f}@??sOgd@"
    ]
  },
  {
    "zip": "11004",
    "polylines": []
  },
  {
    "zip": "10468",
    "polylines": [
      "cboxFvl}aMz@jCbVfJrg@ve@r`A~k@??{Ovt@{@~MzJd[`LnMtIvEcBjHcGS??ce@{c@??~CaI{JsN_]iMgOiYsXwHgJ_HrDcGn_@_IcrAwcA??fc@oP"
    ]
  },
  {
    "zip": "10454",
    "polylines": [
      "{pbxF|udbMv[obAzEo_@q@qM??zWuC??`@|Fv`@d[vGzJnFfJSjM??wL~\\kRbV?r]sIfEsXzT??_g@gaA"
    ]
  },
  {
    "zip": "10456",
    "polylines": [
      "gpgxF|ccbMvGcBbG_ScGyBc[jCz@w[~C_DrSrIrI_]nAgT??nPcG??vGfOvy@rXnPS??bGvBjCvGsIlk@sDwB??k\\sSgEnUg@fT_Ir]_IgEgEz@g@jC??kMoFka@o_@{EcB"
    ]
  },
  {
    "zip": "11238",
    "polylines": [
      "eviwF~vnbMo@sK}Kab@mBa]`F}RrCM??t~@mKbo@hP??eEp\\ls@qIl@hS_BdEqRdN_VfDyDjE??gHhD??a\\jLq^wIeUtOoHp@KgD"
    ]
  },
  {
    "zip": "11204",
    "polylines": [
      "ym_wFxmpbM~[gS??|CbJdHqMkAcDfyBcV??bHhxA??qDFwSpl@eGfEmTf_@??gTgU??}}AmbB"
    ]
  },
  {
    "zip": "11210",
    "polylines": [
      "sl`wF~}ibMhGe@cC_{@zMk@lL}ROyD??dv@iBbOpMxAhO`i@xg@??x^jo@??cyBhWgAmA{YxCmEhF??qKu\\]c[yGsC"
    ]
  },
  {
    "zip": "11358",
    "polylines": []
  },
  {
    "zip": "11416",
    "polylines": []
  },
  {
    "zip": "11370",
    "polylines": [
      "{z}wFfa_bM{QfFsQgD_HqGcCqTbQgYfEs]tKmWdWiW??fJf@rDrNz@~a@uEvf@??}BvUwQnF?zJ",
      "{_{wFj}~aM~QaO??bg@{L??QqPhOuGns@kI??vHl}A??sb@zC{c@sW}Gfk@??gHoAyTwXcJmM`ByCoDgCaJS"
    ]
  },
  {
    "zip": "11364",
    "polylines": [
      "gfvwF`~haMeEiXiHkUiK}_A~Ch@|TmPqNab@_NbJsFhOuVb@??XmHjR}k@|]e]vm@sv@`JkCbKT??bR~V~`@ja@|A`I}JbBtRjvB??s^vPhGxZyaBri@"
    ]
  },
  {
    "zip": "10278",
    "polylines": [
      "onowFl~tbMbC{G??jHhAaFdKmEsD"
    ]
  },
  {
    "zip": "10279",
    "polylines": []
  },
  {
    "zip": "11365",
    "polylines": []
  },
  {
    "zip": "11417",
    "polylines": []
  },
  {
    "zip": "11371",
    "polylines": []
  },
  {
    "zip": "11359",
    "polylines": []
  },
  {
    "zip": "10090",
    "polylines": []
  },
  {
    "zip": "11211",
    "polylines": [
      "i`qwFrrlbMjJqRtB{WxTc\\bB}IoEacAt@mK~KwDaPy`A??zQaF??zTlhA??pH~c@pIx_Aj\\{Bn\\nk@pFbAKaC??~B]zD~b@wKgC}c@vl@wEnA??a`@}@cAOgBsBaFSyM}C}i@ya@gG}A"
    ]
  },
  {
    "zip": "11205",
    "polylines": [
      "}fmwF`ipbMcAiEk@cAwIu[wG_NtJiKX[RwB??vEoA|c@wl@vKfC{D_c@_C\\??eA{SxBeBzq@cI??jPba@??sCLaF|RlB`]|K`b@n@rK??sLnA??eU`Cw@p_@{FdEuHvBsx@^"
    ]
  },
  {
    "zip": "11239",
    "polylines": [
      "}|awF`o~aM_J{DaHnI{Tsp@~]{UmEcM??lYqR??z@lBhd@eRxCv@tSxXsC~HuJdKwMj@??h@tR_k@nm@"
    ]
  },
  {
    "zip": "10457",
    "polylines": [
      "{~jxFbp`bMzEc[zTon@bGgY??z^pKzJrInUd^{E|Jrb@lU??oAfTsI~\\sSsI_D~C{@v[b[kCbGxBcG~RwGbB??c`@oK??_DnAoFiEvBcGwQaV_q@ic@"
    ]
  },
  {
    "zip": "10168",
    "polylines": []
  },
  {
    "zip": "10154",
    "polylines": []
  },
  {
    "zip": "10034",
    "polylines": [
      "gjlxFn_gbMsd@oOzDpGcDlD??wo@ce@pCcWbEcCfIvA~HaIoBeEuJvDbF_QbFef@zCcDbVdB~t@hj@??sAlQvHjIwg@~Y_GhUZhFjM~E"
    ]
  },
  {
    "zip": "10020",
    "polylines": [
      "iywwFllpbMj@iN??fBqF??tBzA??xBvA??cGbS??_C{A"
    ]
  },
  {
    "zip": "11101",
    "polylines": []
  },
  {
    "zip": "10021",
    "polylines": [
      "yo{wFv{nbMgIaLhKw[??x@aShKyi@xPii@pIyJjEq@??|fA|`A??ef@rzA??o^fG??wVcIoCfK}Nu@_G{D"
    ]
  },
  {
    "zip": "10035",
    "polylines": [
      "_saxFtkhbMjLoj@??rYqQdZsGtVzAnF`H??_K|LyDdL|BhBa\\~cA??iGtSeCgBpGmS_GmD??JiL}NeJ_C~H}VwP",
      "qp_xFbgdbMvEcMtTgJrDf@~Wja@rb@vQnFvElLdPL~CkPln@_E`EqIe@{VqSiJqNi^{RuInAcLmA{FgFEePfO{\\"
    ]
  },
  {
    "zip": "10009",
    "polylines": [
      "ybswFzfpbMjP}g@??t_@sI??hh@bS`FZcP|_A{G`R??mgAmt@"
    ]
  },
  {
    "zip": "10155",
    "polylines": []
  },
  {
    "zip": "10169",
    "polylines": []
  },
  {
    "zip": "11249",
    "polylines": []
  },
  {
    "zip": "10023",
    "polylines": [
      "}w{wFh{qbMc_@{Yfg@ucA??~FzD|Nt@nCgKvVbI??fAjBiJzO~FbJ|G~DdCzLm^diA??ku@w`@??lLq@"
    ]
  },
  {
    "zip": "10037",
    "polylines": [
      "eqcxFtegbMjr@bAdWsF??kLnj@??gSlJ??of@m[??mA_T"
    ]
  },
  {
    "zip": "11103",
    "polylines": []
  },
  {
    "zip": "11102",
    "polylines": [
      "ui|wFlmdbMhAaC`LiCnNvPvKmGlZme@??pp@jo@??q^rgAgBrN??}LyEqBhMgEbBqD]yGuCoSqJq@}FlDwNdBAjCgFSyM{]_k@oDeAs@Q"
    ]
  },
  {
    "zip": "10036",
    "polylines": [
      "iuwwFhopbMbGcS??xNlJ??~B~A??rJvG??cGbS{B_Bmj@jgBbGpE??fUnY??yWwOkRyPw@wDwWmS??xIVrVuk@{B{A~EuPrDgLbCnAzGsT"
    ]
  },
  {
    "zip": "10022",
    "polylines": [
      "mxxwFx{nbMuB{A??df@szA??``@`]??xAlNiBrGyB{AiKd\\@pK??eCzH??kGfS??uB{A??cCuA??{BcB??}BoA??yRqM??dC{HgC_B}B~H"
    ]
  },
  {
    "zip": "10152",
    "polylines": []
  },
  {
    "zip": "10026",
    "polylines": [
      "og`xF|kibM~FlDqGlSdCfBhGuS??nUpOiF`TjAhI??wSpa@??{JwGuNVmOwJvUeu@nK_P"
    ]
  },
  {
    "zip": "10032",
    "polylines": [
      "muexFvmhbMlGdEgUxs@gXuA??mq@iSoQnDuQN??dDiXdHeC|OpDrDcZhJeYdVv@pd@nYtP~E"
    ]
  },
  {
    "zip": "11106",
    "polylines": [
      "aqxwFhxdbMbHmUp\\~W??t^xYeg@phA}RpXiDpK??qI}@s[{^Q_R??fBsNp^sgA"
    ]
  },
  {
    "zip": "10033",
    "polylines": [
      "gjlxFn_gbMjH`Bvh@r`@rYscAdZtJvCkG??zbApf@??fb@hb@??uP_Fqd@oYeVw@iJdYsDbZ}OqDeHdCeDhX??aHyLmo@ah@qk@w^_MmD{@vBaDmA??bDmD{DqGrd@nO"
    ]
  },
  {
    "zip": "10027",
    "polylines": [
      "m}cxFzajbMdAmCxHPrIhJlSqJjFqPvBaT??fSmJ??|VvP~B_I|NdJKhL??oK~OwUdu@lOvJtNWzJvG??_C`H_QyDmKl\\cLvEiKqH??tAyD{BwAoA|D??gIlH??cBW??s]}QyRsU??dIRrMub@yCcMiReM"
    ]
  },
  {
    "zip": "10153",
    "polylines": []
  },
  {
    "zip": "10151",
    "polylines": []
  },
  {
    "zip": "10031",
    "polylines": [
      "o|fxF`fjbMfXtAfUys@mGeE??xBmHnHtBn^dU??dJtb@??hRdMxCbMsMtb@eIS??_]cUk_Aad@"
    ]
  },
  {
    "zip": "10025",
    "polylines": [
      "i~axFbbmbMtBrA??hKpHbLwElKm\\~PxD~BaH??vSqa@??pJpHvCUOgLzSfGvO`O??{Kx`@nGfH|HdQwYp}@aZiFeXgJqiA}t@??fImH"
    ]
  },
  {
    "zip": "10019",
    "polylines": [
      "s{ywFdaobMn^gG??tBzA??~BzA??xRpM??aGvRzB~AbGgS??zBbB??yApFtBtA??gDpKzBvA??~BzA??{GrTcCoAsDfL_FtPzBzAsVtk@yIW??o`@qP??l^eiAeC{L}G_E_GcJhJ{OgAkB"
    ]
  },
  {
    "zip": "11105",
    "polylines": []
  },
  {
    "zip": "11104",
    "polylines": []
  },
  {
    "zip": "10018",
    "polylines": [
      "a}wwFlrtbMcGqElj@kgBzB~AbGcS??hRzL??}k@hkB{MoIyEjO"
    ]
  },
  {
    "zip": "10024",
    "polylines": [
      "qhbxFpkmbMpiA|t@dXfJ`ZhFvYq}@}HeQoGgHzKy`@??nCc@??fJM~`@~YPbH??nSbV??iKv[fI`L??gg@tcAb_@zY??mLp@??_YkUy]qPolCciB??bBV"
    ]
  },
  {
    "zip": "10030",
    "polylines": [
      "shdxFd~hbMzXob@??nf@l[??wB`TkFpPmSpJsIiJyHQeAlC??eJub@"
    ]
  },
  {
    "zip": "10178",
    "polylines": []
  },
  {
    "zip": "11243",
    "polylines": []
  },
  {
    "zip": "10161",
    "polylines": []
  },
  {
    "zip": "10175",
    "polylines": []
  },
  {
    "zip": "10029",
    "polylines": [
      "_j_xFhdkbMkAiIhFaToUqO??`\\_dA}BiBxDeL~J}L??dKh\\~f@fZ`P|W??eFdCsShp@tBrAqKp[??oCb@??wOaO{SgGNfLwCTqJqH"
    ]
  },
  {
    "zip": "10015",
    "polylines": []
  },
  {
    "zip": "10001",
    "polylines": [
      "yfwwF|lubMgUoY??xEkOzMnI|k@ikB??h^hV??zBrAuGbSbG|D??mQh_@qIh]D|FsJ~[kJx@??eZuK"
    ]
  },
  {
    "zip": "11109",
    "polylines": []
  },
  {
    "zip": "11691",
    "polylines": []
  },
  {
    "zip": "10014",
    "polylines": [
      "_orwFrhtbMr`@tO??cBb`@rN~LpK|D??yKbX??iDeAvBoVqEkA_gBcJ??jOcl@`d@mRxKzG"
    ]
  },
  {
    "zip": "10028",
    "polylines": [
      "gb|wFxzlbMFkI}D{EjGgSxBzAvCmItHaWuBgBjPmi@|JvGdDwI??rPjT??kEp@qIxJyPhi@iKxi@y@`S??oScV"
    ]
  },
  {
    "zip": "10174",
    "polylines": []
  },
  {
    "zip": "11256",
    "polylines": []
  },
  {
    "zip": "11242",
    "polylines": []
  },
  {
    "zip": "10176",
    "polylines": []
  },
  {
    "zip": "10162",
    "polylines": []
  },
  {
    "zip": "10002",
    "polylines": [
      "u_qwFvtrbMhDmW??zGaRbP}_AaF[ih@cS??lp@`Jxh@jOvLzJ~CfO`Cvc@uDd`@??tAxX}]lH??sf@{T??mVmH"
    ]
  },
  {
    "zip": "10016",
    "polylines": [
      "mzuwFf`qbMiR{L??x[{cAVyL??dYdUzPpCdS`J{E|Q_Wvl@iKjP??i^iV"
    ]
  },
  {
    "zip": "11693",
    "polylines": []
  },
  {
    "zip": "11692",
    "polylines": []
  },
  {
    "zip": "10017",
    "polylines": [
      "swvwFxlobMwCk@??KoJ??yB_B??{BsA??AqKhKe\\xBzAhBsGyAmN??pc@~a@??[h@??WxLy[zcA??sJwG??|B_I{BuAaCtH??yNmJ??yBwA??jGgS??rBzA??~BzA??`AdF??hFiC"
    ]
  },
  {
    "zip": "10003",
    "polylines": [
      "c`twFhkrbMh\\mcA??lgAlt@??iDlW??yMuCiKtMqOn`@??_GiSwk@s_@"
    ]
  },
  {
    "zip": "10177",
    "polylines": [
      "}~vwFbqobMaAeF??|BfB??{@|B"
    ]
  },
  {
    "zip": "11241",
    "polylines": []
  },
  {
    "zip": "10173",
    "polylines": []
  },
  {
    "zip": "10167",
    "polylines": []
  },
  {
    "zip": "10007",
    "polylines": [
      "onowFl~tbMlErD`FeKkHiA??tFyN??hGnA~Iro@dHbG??iBpF??oStM??aFzN??aNmT??xL}\\{H{Ft@mL"
    ]
  },
  {
    "zip": "10013",
    "polylines": [
      "kmqwFhytbMrKtBjGeLbPud@_@}J??rf@zT??aAtP??uFxN??cCzG??u@lLzHzFyL|\\??qKd@??sRoC??qK}DsN_MbBc`@"
    ]
  },
  {
    "zip": "11697",
    "polylines": [
      "q`qvFdn|aMdaBnzIY?i}@G_Dw@??}SeXmIcP}AuUlAoR_BoPiBcMwLsX^uMjDmDrBkJuCem@{R{SaImRz@asA{X_z@_QeK??~JeBbc@~@~^`mAjGkF"
    ]
  },
  {
    "zip": "10012",
    "polylines": [
      "kkrwFf`tbMpOo`@hKuMxMtC??lVlH??^|JcPtd@kGdLsKuB??s`@uO??rBkG"
    ]
  },
  {
    "zip": "10006",
    "polylines": [
      "oinwFphvbMhBqF??bClB??dA~@??`BjA??fHfG??pKtW??sd@kM??bByQ"
    ]
  },
  {
    "zip": "10166",
    "polylines": []
  },
  {
    "zip": "10172",
    "polylines": [
      "_awwF|iobM_C{A??lCcI??xB~A??gC~H"
    ]
  },
  {
    "zip": "10199",
    "polylines": []
  },
  {
    "zip": "10170",
    "polylines": []
  },
  {
    "zip": "10158",
    "polylines": []
  },
  {
    "zip": "11252",
    "polylines": []
  },
  {
    "zip": "10010",
    "polylines": [
      "epuwFt_nbMZi@??xZzShp@pMvO{B??kP|g@??i\\lcA??uV|G??cG}DtGcS{BsA??hKkP~Vwl@zE}QeSaJ{PqCeYeU"
    ]
  },
  {
    "zip": "10004",
    "polylines": [
      "qsmwF`qvbMfQqT??`FtHv@tFxEq@??`CpNHqFoE_T{JgP??tMhQlCrIr@hTg@rBaFx@??wR~C??qKuW",
      "ailwFz~{bMGK]k@h@qBBIxGoGHGtx@t`@NHtFhEsA~E{@|CcG|DeCmAcw@{d@iAoB",
      "swjwFnmxbMaHkGWqLfBcJvDcMjG_IbKo@nDxDl[`s@fBzJGr@??yT~Bya@uO"
    ]
  },
  {
    "zip": "10038",
    "polylines": [
      "ubowFvetbM`AuP??|]mHuAyX??hEdb@`KxYhQf]??kHkL_Xvc@??cCmB??eHcG_Jso@iGoA"
    ]
  },
  {
    "zip": "11694",
    "polylines": [
      "youvFn~naMhh@pxC|dBbuG??kGjF__@amAcc@_A_KdB??_Ck[wf@glAfCea@?ge@o^opB_CaFqF_C??xRdE~RaEkQkz@jEI"
    ]
  },
  {
    "zip": "10039",
    "polylines": [
      "muexFvmhbMgb@ib@??dVnBbv@}FdXI??lA~S??{Xnb@??o^eUoHuByBlH"
    ]
  },
  {
    "zip": "10005",
    "polylines": [
      "{_nwFlfvbMeA_A??~Wwc@jHjL??zJfPnE~SIpFaCqN??mI}SeDbD??gQpT??gHgG??fCsEuAwAsC~E"
    ]
  },
  {
    "zip": "10011",
    "polylines": [
      "ywtwFftrbMtV}G??vk@r_@~FhS??sBjG??yK{Gad@lRkObl@??sc@mE{@rI{R{I??jJy@rJ_\\E}FpIi]lQi_@"
    ]
  },
  {
    "zip": "10171",
    "polylines": []
  },
  {
    "zip": "10165",
    "polylines": []
  },
  {
    "zip": "10466",
    "polylines": [
      "cfrxFrbyaMcQkCgOsIbLod@sIc`@sIwG_Ig@sIsDR_D??vBsSv[kMvLbBjRcGrX{uAf@cGcGS??rDgT??rNrX??rg@b|A??fJjWoZbrA??wQjz@rI~CjCg@~f@jRq@|D}yAme@gJcL"
    ]
  },
  {
    "zip": "10314",
    "polylines": []
  },
  {
    "zip": "10472",
    "polylines": [
      "osfxF|{|aMbBeG}KeN|A}_@~Mcy@??fe@yoB??n]xvF??gw@sD{EoAg@sIoKy@"
    ]
  },
  {
    "zip": "11220",
    "polylines": [
      "waawFzusbMfwAd{A??yLhV??c[f{@uRx|@_EmAuG}Jy@iKlAiToRx`@??uIcFcCuAqa@ae@??n`@ki@}a@{c@vx@g_B"
    ]
  },
  {
    "zip": "11234",
    "polylines": [
      "q`~vFvpsaMnvAjC??nKnKs]vVs{@s]wG_I",
      "uwyvFjswaM{@zJ{TbL{Jz@_]kHjHkp@f^z@~W~\\",
      "e`|vFv_yaM{@nPwGf@nAwBSgJoi@wB_S{^~Cgc@{JwLvB{End@kWzErN?~MzOju@bLb[",
      "mw{vFbm|aM_q@_Sk\\_v@~MoKjk@bGjHb[rIfr@",
      "uwtvFbgzaMjC~H??oZfJwZo_@sEjCnKjHbBrScV~CoKcLg@{ErIw[~R_IrN~Cn_@rX",
      "me_wFrktaMRQjHyG??jk@j\\ka@fTgJgJwG_]",
      "mq~vFnnvaM{@z|@c[kMsX_v@rIcVjW~HvGbLzJnF",
      "ahyvF~avaM_Sb[sDcBwGkRgj@wIwJwOzEg@pBxD|GxCrI{TgE{Obt@rNnKrb@",
      "qxwvFvfxaMs]fm@kMwVvQs{@fOnF~Hr]",
      "sl_wFtegbMeBsOyl@eeA??jw@oEvHka@~FeO`CnC??oM`^|AjBzA[bdAm{B~jAiy@tCbI`Frx@gk@ze@gX~^vg@gg@~O}GdShBfF|}@eStYoYcM}PqC}@v@vFhM~Vn[hg@ci@kA}fBkLopAb|A}n@je@?xYvV`Efo@aEnIzLhk@aWnn@{E~DaBQBoCnDmLuCoIeNYaKtEeBxD|Dnd@cGxK_MiDa^jRsZp^xErYqAdFsYr[_@`FbErGvkAk`BxLwAtIpQ??a{@rcAoDbDcEoHa]d`@mM_UmSvU_F~NlD|Gi\\z`@zAvCyA|B_P~A??ai@yg@yAiOcOqMev@hB"
    ]
  },
  {
    "zip": "11208",
    "polylines": [
      "k_iwFbp~aMq\\cd@{CmDwCyFwCwKwRe_@kFa^??z_@oGzBYlC[zBk@nX}DfFg@??rXyX??v\\kF??vQiCUeE~PiN`MsB~GkAhF_AvRfLhDxWHXvL~C??hLyHpGkC~CmErNgJ??zDrErVo@lFv_@eXtHqCvInAPfAuDrOsDzBhAfDvW}C`PmFxD??mYpR??u[zS~AoXyD}LeTlOcElJkZzRwTpJc_BhVbD~IcI~F"
    ]
  },
  {
    "zip": "11354",
    "polylines": []
  },
  {
    "zip": "11432",
    "polylines": []
  },
  {
    "zip": "11426",
    "polylines": []
  },
  {
    "zip": "11368",
    "polylines": []
  },
  {
    "zip": "11369",
    "polylines": []
  },
  {
    "zip": "11427",
    "polylines": []
  },
  {
    "zip": "11355",
    "polylines": [
      "_wvwFbktaMaYes@aS}dAcF}c@tA?|A{^??liAfIzBse@|C{@??ni@zI`@xQnQ^|A{P??qAl~@qSvs@kFfnA|@|J??uX}OwGyAyJjAyXjQ"
    ]
  },
  {
    "zip": "11433",
    "polylines": [
      "kvmwFx~haMfEaBAaNzLoD??j[mK~[mV??|On]r[|cAlFnUUfEiCzBzHdT??qDg@oF|C}EfEx@jCma@z\\sc@tKw@oJ??aUu_AuLqKkCoPeCkk@"
    ]
  },
  {
    "zip": "11209",
    "polylines": [
      "uhawFfuzbMnRy`@mAhTx@hKtG|J~DlAtRy|@b[g{@??pk@jMp\\pXi@tAvShQfS|HdBgFeReJzAwDvBiFl]|IrNo[p@qIcCgGpCsGnZh[??aEjc@gF|j@et@`i@iHdAsu@|KqInA{IsBic@cKe\\uHuUcNiTgM"
    ]
  },
  {
    "zip": "10103",
    "polylines": [
      "u|wwFvoobMcGfS{B_B`GwR??|BnA"
    ]
  },
  {
    "zip": "11235",
    "polylines": [
      "e`wvFhblbMcRegD??|A`Cl_@cItZy`@}FulAlNgJfJy@}Lh|DbCddAlAnGvEaA`@qdCd^eBbGbLlCtKeAtl@dApfBfOphB??kG@wDmp@al@qHcBhWeGrB??_BcVeGgHwc@cGuCoe@"
    ]
  },
  {
    "zip": "11221",
    "polylines": [
      "aflwFjdfbMgEyLlW_j@{@mUfZ{m@??jZlZ|G~GxGbH??Yd@aCtFtAlSvCa@lJpmB??~Bva@cu@`J??kLefAk]cUyGwI"
    ]
  },
  {
    "zip": "10473",
    "polylines": [
      "ceexFtxuaM_A}N??zr@_NzJjMbo@~W?rDcLrDsI~RRnKcBfJwGvBnAf@nFoAjCsIRwLjH{OrXrDnKwLjC?z@vGcGbVnFrIcBbVoFvBkWbBg@~MvBzEcBf^kWnUoK~f@oKvQsXbV??{@f@??o]yvF"
    ]
  },
  {
    "zip": "10467",
    "polylines": [
      "o}qxFzj}aMcJoUwGkz@~C_b@fEkR??fJbL|yAle@p@}D_g@kRkCf@sI_DvQkz@??be@~Rrq@bLzfAvB??vB???vGj_A??bBnZaXC??yTkPwQ`FgJ|Zct@`SwLtG??gc@nP??ka@vB??wScV"
    ]
  },
  {
    "zip": "10301",
    "polylines": []
  },
  {
    "zip": "10459",
    "polylines": [
      "oifxFzz_bM{F{ObHwBnP{m@k\\cVRiC??nKx@f@rIzEnAfw@rD??z@g@??zEwB??sDzOnFfOja@~f@??{Ynn@??oPRwy@sXwGgO"
    ]
  },
  {
    "zip": "10471",
    "polylines": [
      "ogvxFrsbbMly@gdE??\\gD??fr@~HjZvV??vSbV??~Wn}@oFz^kWj_AoApUb[lAmAtW??u_Div@kMoF"
    ]
  },
  {
    "zip": "10303",
    "polylines": []
  },
  {
    "zip": "10465",
    "polylines": [
      "wtkxFzfpaMRkHzOR~HnUbQcLf^oFjCbBrN{@jCsDrISfEfE~f@vB|VoC??lDM|V{LxJ{E~CmDpd@sg@|@sCn@wB~Mqc@TO??pPl[f@~H_D{@kRzTjWgJnP_XvQo}@jHgEfErIg@rIoZrq@z@rN{Yrg@_D~f@nFnd@bGzTvBrXja@nFkCja@od@fT_XwBoFnAwQwGgJSsg@zT??gO{@gY{T?{h@nAoK~HkHbGrIoPc[{J{@knAzJc[oF??{m@kz@"
    ]
  },
  {
    "zip": "11237",
    "polylines": [
      "inowF~~dbMjQjD??jFaJnMsCdILrb@my@nNkHdKkA|@eB`OoZHMDKHUdXiP??}Hxg@??gZzm@z@lUmW~i@fExL??gHgHoKjUs{@|U??{TmhA"
    ]
  },
  {
    "zip": "11223",
    "polylines": [
      "yjzvFzynbMkFibA??h[cHttAcJ??tCne@vc@bGdGfH~AbV??dA~w@??{@zImuC~\\??cHixA"
    ]
  },
  {
    "zip": "10115",
    "polylines": [
      "szaxFvdmbMuBsA??nA}DzBvAuAxD"
    ]
  },
  {
    "zip": "11357",
    "polylines": [
      "oq}wFnasaMmRuSqEqBwEh@q[ca@aGeMjWoi@vBqZuAcc@hIuo@vCuD`OpAtMyF~@kBcHaB??`MkKzM`]x`@qG{@mPxe@kDfAzF??_DlkA??_LfsC??{\\qOFhLiPdUw^tD"
    ]
  },
  {
    "zip": "11419",
    "polylines": []
  },
  {
    "zip": "10060",
    "polylines": []
  },
  {
    "zip": "11418",
    "polylines": []
  },
  {
    "zip": "11430",
    "polylines": []
  },
  {
    "zip": "10048",
    "polylines": [
      "slnwFj{vbMkPcC??nSuM??cBxQ"
    ]
  },
  {
    "zip": "11356",
    "polylines": []
  },
  {
    "zip": "11222",
    "polylines": [
      "}gswFfxlbM}R_u@zAsHpIga@F[dJw[nTsMbA[zJ_NhLwq@vGwGfg@uW??`Px`A_LvDu@lKnE`cAcB|IyTb\\uBzWkJpR??a@NwM@_KHqCTkIt@oBn@uCDkCj@iOU"
    ]
  },
  {
    "zip": "11236",
    "polylines": [
      "mfcwFxvdbMt@ubAiIoq@yG_N??a@mF`VmDv@cAsEgMxh@id@??~j@om@i@uR??nQN|XfFbo@p_ArP~CdE~DrAj]mI`HoK~Rg\\t}@??aCoC_GdOwHja@kw@nE??_z@pBcJl@uA|A"
    ]
  },
  {
    "zip": "10128",
    "polylines": []
  },
  {
    "zip": "10302",
    "polylines": []
  },
  {
    "zip": "10464",
    "polylines": [
      "gohxFpufaMX|HHxBuTdT{h@fC{[gAu@kDkBwIMm@xQkYzJsCvBm@tBm@|x@rDVzG",
      "c`pxFrtkaMbj@~Wjf@rb@nFnAf@zEkMj\\vGsD~HkRvG{@zEgOwj@k\\kCoPgT_DgE~CgJkHcGoKoA{JbGRjC_SpCyE??nK\\t[bAjPf@??nFv[bj@~HvBvGvVnFvBbLnFrInFnAJgB|GeC??~R~IjD|AE\\UpB??u]vZwGjC{h@gEcBfEnKbBbGjHsXnUwGnP{@fOsI{@cL_IkMnFnKnKR~C{EnK??gJkHsXoA_eAgTgO???~a@kjC",
      "mcixF~ekaMyQoGs]vQoFwBwGgJ?gEvBSD???zV_CJQfMcStZcOfBAzLMbM^nTmEDABB|FlG`D`GqFpHaLbHeKnGe[rP_@IoGuA"
    ]
  },
  {
    "zip": "10470",
    "polylines": [
      "weuxFrawaMfOzJrDkMsDsDrIk\\fEwB??S~CrIrD~Hf@rIvGrIb`@cLnd@fOrIbQjC??gEjR_D~a@vGjz@bJnU??kZwVgr@_I??b`@otBct@{^gEoFRsI"
    ]
  },
  {
    "zip": "10458",
    "polylines": [
      "mkkxFj~{aMVdGpNpPb`@bQ??cGfY{Tnn@{Eb[??s`A_l@sg@we@cVgJ{@kC??vLuGbt@aSfJ}ZvQaFxTjP"
    ]
  },
  {
    "zip": "10312",
    "polylines": [
      "s{tvFlzqcM~ByF|e@ea@vFB`I~MLbV|WzbAbGrIn\\bHrByD??v\\gCps@sLrx@c~@bCyFyBoC`Moa@??pAfB??xBlWbo@~jA|k@`jBmAxH_CfO~b@zfA??eOg@oh@~YwZeC{e@|Hcp@rTybAf~@iJhC{Lsq@??iNi\\w^id@yI_Gu`AjX??hFka@mGaPhAqLhVaQrKy]n[qQ`EqFeFsu@iOwt@cBfB`AdWnEtUlF|EzCtQ??sWb@gLuMcG{Ssg@ugA"
    ]
  },
  {
    "zip": "10474",
    "polylines": [
      "sybxFrt_bMka@_g@oFgOrD{O??nK}CbV}YbLsg@fJcGv`@kMja@dVbBlP_DRsDzEcBb[zEj\\oUlRoFhMg@b[vBzh@`FX??{WtC??yi@wm@"
    ]
  },
  {
    "zip": "10460",
    "polylines": [
      "oujxF~b{aM~\\{Ezm@~CjCkCgJsSfJ{JzJcG~k@sI??_Nby@}A|_@|KdNcBdG??ShCj\\bVoPzm@cHvBzFzO??oPbG??sb@mUzE}JoUe^{JsI{^qK??c`@cQqNqPWeG??`XBcBoZ"
    ]
  },
  {
    "zip": "10306",
    "polylines": []
  },
  {
    "zip": "10110",
    "polylines": []
  },
  {
    "zip": "10104",
    "polylines": []
  },
  {
    "zip": "11232",
    "polylines": [
      "_qfwFvvsbMhr@sh@~}@z`AzSsWfOcY??xVrX??wx@f_B|a@zc@o`@ji@??_GyGob@_f@??oBwCU}\\oQu[sFgSlD_XoA_DgEwBc[cBuLiE"
    ]
  },
  {
    "zip": "11226",
    "polylines": [
      "eybwFnmnbMkRun@kFafB??d_BiJbFpQ??xGrC\\b[pKt\\??hPrb@iPnH??so@rGuc@ViE{N}LpHnK~_@e@jBsCoB"
    ]
  },
  {
    "zip": "11385",
    "polylines": []
  },
  {
    "zip": "11420",
    "polylines": []
  },
  {
    "zip": "11434",
    "polylines": [
      "aoiwFp|kaM{HeThC{BTgEmFoUs[}cA}Oo]??pD}CvPAhAnP~EnPdTjE|Vkd@sNyGyReWrh@cV??vKcD|\\sVrIdg@hMe@|a@`Fx[dLhR|BdLw@d@zH??m@lA??qS`e@{Onh@mJhx@qHeB??oNYg^vCqbAnOcLxG??yBlA"
    ]
  },
  {
    "zip": "11435",
    "polylines": []
  },
  {
    "zip": "11421",
    "polylines": []
  },
  {
    "zip": "11233",
    "polylines": [
      "k_iwFr~gbMmJqmBwC`@uAmS`CuFXe@??xAqCnk@egAzSJ??xy@jgC??av@yC{NvN_Xbl@n@`R??qQtB"
    ]
  },
  {
    "zip": "10105",
    "polylines": []
  },
  {
    "zip": "10111",
    "polylines": []
  },
  {
    "zip": "10461",
    "polylines": [
      "g~jxFrbyaMwB???z@kqBvQwkBnFg@??b[nFjnA{JzJz@nPb[cGsI_IjHoAnK?zh@fYzTfOz@??cQjHgTcVgESS~a@im@j}@aBcToA?_tA~z@"
    ]
  },
  {
    "zip": "10307",
    "polylines": []
  },
  {
    "zip": "10475",
    "polylines": [
      "ccqxF~_paMfO?~dAfTrXnAfJjH??{EbGgYf@{EgE_NkCoi@gE{JnFsD~R??sNsX??nFoZ",
      "kroxFfrtaMsg@c|A??bLwQbQS~u@bQb`@_IbBgJb[oAnFgE??vGfJvQn}@kRgO{TrNsjA~a@c[fO"
    ]
  },
  {
    "zip": "10305",
    "polylines": []
  },
  {
    "zip": "10463",
    "polylines": [
      "whqxF~a~aMja@wB??brAvcAo_@~HsDbGfJ~GrXvHfOhY~\\hMzJrN_D`I??a]kWiCoAgTqFwMbLsHb[gOxe@_DjREP??sr@iX??lAuWc[mAnAqUjWk_AnF{^_Xo}@"
    ]
  },
  {
    "zip": "10311",
    "polylines": []
  },
  {
    "zip": "10107",
    "polylines": []
  },
  {
    "zip": "11219",
    "polylines": [
      "qyawFf|rbMjQq^??jJ|Pvi@mcAfBrB??|}AlbB??sy@x_B??gwAe{A??yVsX"
    ]
  },
  {
    "zip": "11225",
    "polylines": [
      "qlfwFvykbMbEa_A??lUv@~@y`@~JyOlDP??T`PlSb]nRy@??jF`fBjRtn@??eQxB{DnDoKjA??gAQ{PjZyZm]}RcByIgHyBcF??xDkE~UgDpReN~AeEm@iSms@pIdEq\\"
    ]
  },
  {
    "zip": "11231",
    "polylines": [
      "qpiwFjwubMlDyVOqNwKmEd[yeA??lJrF~DeL|DsB??lSvJj@kAjBrD}AdRhC~EfX~R??tLhEb[bBfEvBnA~CmD~WrFfSnQt[T|\\nBvC??IKmf@jCy^pBes@xDIH??}m@{jA"
    ]
  },
  {
    "zip": "10098",
    "polylines": []
  },
  {
    "zip": "11379",
    "polylines": []
  },
  {
    "zip": "11351",
    "polylines": []
  },
  {
    "zip": "11423",
    "polylines": []
  },
  {
    "zip": "10271",
    "polylines": [
      "y|mwFxhvbMaBkA??rC_FtAvAgCrE"
    ]
  },
  {
    "zip": "10270",
    "polylines": []
  },
  {
    "zip": "11422",
    "polylines": [
      "sbiwFpv_aM|Jgf@??|GJhACjRPbVvIdw@pC??lnAsVjCdBfFvSj@tKfAnCpAfS|Ndh@zEg@bOlCzf@gDjIaA??r@jMmLgGyBjD|AzL??lAvFsFjH{JImPrKuNtZp@`AfQg[~NsE`]lC`c@l{AzOjRzQ`A|JzM?fT{TsD{EfEoZzaAgE~CkC~MoKjMf@~CkHfJku@b_Cs]by@{c@jHsXgE_IkWnA_l@cG~k@~Hv[~\\rIjk@{JbB~CkHz@?nKzEbB??kp@hLon@~SoGo@??lMugBy@iN??jGpBlDcWbB|EjR]xOoHbAwG~[oPi@mAlXi[`EeQ_@iMbWoAlb@}~A{DoTmt@y^}ObI{[fkArBtQc`@d\\{MGK}Ghu@ucC}CgLuIgFiN~O}DU??l@mA??bdA}wBz[{[cLaCc{@`W}@zJgHnLgj@cX_O_KmHyJqq@a_@kk@gXs[oJ"
    ]
  },
  {
    "zip": "11436",
    "polylines": [
      "ivhwFpdnaM}SmiA??bLyGpbAoOf^wCnNX???zjA??mf@S_MnAat@|X"
    ]
  },
  {
    "zip": "11378",
    "polylines": [
      "_aswFlhebMrYqj@hP{hAaVeSgHm\\oDsv@??jCyBt|@wE|J}H??`r@flB??zE|J_H|tB??kQkD??mb@fFsa@~[eW|j@sIjHeJwNqF_R|Gkl@"
    ]
  },
  {
    "zip": "10099",
    "polylines": []
  },
  {
    "zip": "11230",
    "polylines": [
      "iv_wFpimbMhPoHiPsb@??lEiFzYyCfAlAbyBiW??lEb{@??jFhbA??gyBbVjAbDeHpM}CcJ??od@_oA"
    ]
  },
  {
    "zip": "11224",
    "polylines": [
      "kiuvFhjpbMeA_x@??dGsBbBiW`l@pHvDlp@jGA??FnTbHbfA??u@|aA}Lpj@oItQwUbE_FkF??wJw^Icf@lCwCdLygAwAqEuMqHmIiPNuK"
    ]
  },
  {
    "zip": "10112",
    "polylines": []
  },
  {
    "zip": "11218",
    "polylines": [
      "w}cwFdynbMnKkAzDoDdQyB??rCnBd@kBoK_`@|LqHhEzNtc@Wro@sG??nd@~nA??_\\fS??gBsBwi@lcAkJ}P??qUiu@en@|GuMsMyFwZtDwJ"
    ]
  },
  {
    "zip": "10106",
    "polylines": []
  },
  {
    "zip": "10310",
    "polylines": []
  },
  {
    "zip": "10304",
    "polylines": [
      "m{}vFpsbcMhCOj^kXbv@dm@dnBdeAdl@b{@??{H|Svd@tk@v^ht@yBhC_TfEyTxXwbA}l@{BsJdBuFqEeKuEv@{JhJuKxJ??gE}N}AiHuCqXlBaE??hCgPqReb@}RkFTvHoStJyI{KdAaFlJsH~CgJoCsScJiE_c@}A}e@fByQq@eTaGsRkPiD}]fb@yZ|V}C"
    ]
  },
  {
    "zip": "10462",
    "polylines": [
      "oujxF~b{aMwGk_A??~sA_{@nA?`BbThm@k}@R_b@fERfTbVbQkH??~@|N??ge@xoB??_l@rI{JbGgJzJfJrSkCjC{m@_D_]zE"
    ]
  }
]